easy_cos/__init__.py
easy_cos/cli.py
easy_cos/cos_core_ops.py
easy_cos/helper_func.py
easy_cos/img_utils.py
easy_cos/io_utils.py
easy_cos/parallel.py
easy_cos/system_util.py
easy_cos/uid_manager.py
easy_cos-0.4.2.dist-info/METADATA
easy_cos-0.4.2.dist-info/WHEEL
easy_cos-0.4.2.dist-info/entry_points.txt
easy_cos-0.4.2.dist-info/top_level.txt
easy_cos-0.4.2.dist-info/RECORD
