Metadata-Version: 2.4
Name: easy_cos
Version: 0.4.2
Summary: A simple wrapper for cos
Author: Jiaqi Wu
Classifier: Programming Language :: Python :: 3.9
Classifier: License :: OSI Approved :: MIT License
Requires-Python: >=3.8
Requires-Dist: cos-python-sdk-v5
Requires-Dist: tqdm
Requires-Dist: pillow
Requires-Dist: numpy
Dynamic: author
Dynamic: classifier
Dynamic: description
Dynamic: description-content-type
Dynamic: requires-dist
Dynamic: requires-python
Dynamic: summary
